inmemdb/InMemDB.py
inmemdb/__init__.py
InMemDB-1.0.0.dist-info/LICENSE
InMemDB-1.0.0.dist-info/METADATA
InMemDB-1.0.0.dist-info/WHEEL
InMemDB-1.0.0.dist-info/top_level.txt
InMemDB-1.0.0.dist-info/RECORD
