Metadata-Version: 2.1
Name: InMemDB
Version: 1.0.0
Summary: GUI-less in memory sqlite relational databases
Home-page: https://github.com/kwe92/InMemDB
Author: Kweayon Clark
Author-email: Kweayon@gmail.com
Classifier: Programming Language :: Python :: 3
Classifier: License :: OSI Approved :: MIT License
Classifier: Operating System :: OS Independent
Requires-Python: >=3.6
License-File: LICENSE
